{
    "data" : {
            "Striver" :[
                {
                "tag":"Array",
                "questions":[
                    {
                        "id":"A01",
                        "status":"0",
                        "title":"Contains Duplicate",
                        "difficulty":"Easy",
                        "link":"https://leetcode.com/problems/contains-duplicate/",
                        "solution":"https://youtu.be/3OamzN90kPg"
                    }
                ]
            },
            {
                "tag":"Two Pointers",
                "questions":[
                    {
                        "id":"TP01",
                        "status":"0",
                        "title":"Valid Palindrome",
                        "difficulty":"Easy",
                        "link":"https://leetcode.com/problems/valid-palindrome/",
                        "solution":"https://youtu.be/jJXJ16kPFWg"
                    }
                ]
            }],
            "Love" :[{
                "tag":"Array",
                "questions":[
                    {
                        "id":"A01",
                        "status":"0",
                        "title":"Contains Duplicate 2",
                        "difficulty":"Easy",
                        "link":"https://leetcode.com/problems/contains-duplicate/",
                        "solution":"https://youtu.be/3OamzN90kPg"
                    }
                ]
            },
            {
                "tag":"Two Pointers",
                "questions":[
                    {
                        "id":"TP01",
                        "status":"0",
                        "title":"Valid Palindrome 2",
                        "difficulty":"Easy",
                        "link":"https://leetcode.com/problems/valid-palindrome/",
                        "solution":"https://youtu.be/jJXJ16kPFWg"
                    }
                ]
            }]
        }
}